ptcgp/__init__.py
ptcgp/constants.py
ptcgp/objects.py
ptcgp/parser.py
ptcgp/scraper.py
ptcgp/utils.py
ptcgp/app/__init__.py
ptcgp/app/app.py
ptcgp/app/components/__init__.py
ptcgp/app/components/select.py
ptcgp/app/pages/__init__.py
ptcgp/app/pages/details.py
ptcgp/app/pages/main.py
ptcgp-0.2.1.dist-info/METADATA
ptcgp-0.2.1.dist-info/WHEEL
ptcgp-0.2.1.dist-info/top_level.txt
ptcgp-0.2.1.dist-info/RECORD
